CHANGES.txt
LICENCE.txt
MANIFEST.in
README.rst
setup.py
TIE.egg-info/PKG-INFO
TIE.egg-info/SOURCES.txt
TIE.egg-info/dependency_links.txt
TIE.egg-info/top_level.txt
doc/build/html/_sources/index.txt
doc/build/html/_sources/intro.txt
doc/build/html/_sources/tutorial.txt
doc/build/html/_sources/api/exceptions.txt
doc/build/html/_sources/api/helpers.txt
doc/build/html/_sources/api/processors.txt
doc/build/html/_sources/api/renderers.txt
doc/build/html/_sources/api/tag.txt
doc/build/html/_sources/api/template.txt
doc/build/html/_sources/howtos/index.txt
doc/exemples/test_template.txt
tie/__init__.py
tie/exceptions.py
tie/helpers.py
tie/processors.py
tie/renderers.py
tie/tag.py
tie/template.py
tie/utils.py