Metadata-Version: 1.1
Name: TIE
Version: 0.1.0
Summary: A minimalist template ENGINE allowing users to define their own simple templating languages.
Home-page: https://pypi.python.org/pypi/TIE
Author: Raphi
Author-email: r.gaziano@gmail.com
License: LICENCE.txt
Keywords: templating
Platform: UNKNOWN
Classifier: Programming Language :: Python
Classifier: Programming Language :: Python :: 2.7
Classifier: Programming Language :: Python :: 3
Classifier: Development Status :: 3 - Alpha
Classifier: Intended Audience :: Developers
Classifier: Operating System :: OS Independent
Classifier: Topic :: Software Development :: Libraries :: Python Modules
Classifier: Topic :: Utilities
